tripod/__init__.py
tripod/api.py
tripod/model.py
tripod/io_utils/__init__.py
tripod/io_utils/io.py
tripod/networks/__init__.py
tripod/networks/modules.py
tripod/networks/tripod.py
tripod/networks/tripod2.py
tripod_ml-0.2.0.0.dist-info/LICENSE
tripod_ml-0.2.0.0.dist-info/METADATA
tripod_ml-0.2.0.0.dist-info/WHEEL
tripod_ml-0.2.0.0.dist-info/top_level.txt
tripod_ml-0.2.0.0.dist-info/RECORD
