Metadata-Version: 2.1
Name: tripod-ml
Version: 0.2.0.0
Summary: Machine Learning tool for extracting latent representations from long sequences
Home-page: https://github.com/adobe/tripod
Author: Multiple authors
Author-email: tiberiu44@gmail.com
License: UNKNOWN
Platform: UNKNOWN
Classifier: Programming Language :: Python :: 3.0
Classifier: License :: OSI Approved :: Apache Software License
Classifier: Operating System :: OS Independent
Requires-Dist: torch (==1.2.0)
Requires-Dist: tqdm
Requires-Dist: numpy
Requires-Dist: bpe
Requires-Dist: requests
Requires-Dist: sklearn
Requires-Dist: joblib
